{
  "FrierenMod:DrawMod": {
  "TEXT": [
    "抽 ", " 张牌",
    " NL 抽 ", " 张牌。", " 张牌。"
    ]
  },
  "FrierenMod:MagicPowerNumMod": {
    "TEXT": [
      "将 ", " 张 *魔力 置入弃牌堆",
      " NL 将 ", " 张 *魔力 置入弃牌堆。", " 张 *魔力 置入弃牌堆。"
    ]
  },
  "FrierenMod:MagicPowerInHandNumMod": {
    "TEXT": [
      "将 ", " 张 *魔力 置入手牌",
      " NL 将 ", " 张 *魔力 置入手牌。"
    ]
  },
  "FrierenMod:ScryMod": {
    "TEXT": [
      " NL  预见 ", "。"
    ]
  },
  "FrierenMod:CostZeroMod": {
    "TEXT": [
      " NL 你手牌中 ", " 张随机牌在本回合中耗能变为0。"
    ]
  },
  "FrierenMod:GainRandomCardMod": {
    "TEXT": [
      "获得 ", " 张在本回合耗能为0的随机普通牌。",
      " NL 获得 ", " 张在本回合耗能为0的随机普通牌。", " 张在本回合耗能为0的随机普通牌。"
    ]
  },
  "FrierenMod:SelfRetainMod": {
    "TEXT": [
      " 保留 手中的 ", " 张牌。",
      " NL  保留 手中的 ", " 张牌。"
    ]
  },
  "FrierenMod:DamageAllMod": {
    "TEXT": [
      "对所有敌人造成 ", " 点伤害。",
      " NL  对所有敌人造成 ", " 点伤害。", " 点伤害。"
    ]
  },
  "FrierenMod:DamageMod": {
    "TEXT": [
      "造成 ", " 点伤害。",
      " NL  造成 ", " 点伤害。", " 点伤害。"
    ]
  },
  "FrierenMod:DamageThirdMod": {
    "TEXT": [
      " NL  造成 ", " 点伤害三次。"
    ]
  },
  "FrierenMod:BlockMod": {
    "TEXT": [
      "获得 ", " 点 格挡。",
      " NL 获得 ", " 点 格挡 。", " 点 格挡 。"
    ]
  },
  "FrierenMod:EnergyMod": {
    "TEXT": [
      " NL 下一回合，获得", " [E] ", " [E] [E] "," [E] [E] [E] ", "。"
    ]
  },
  "FrierenMod:ExtinguishMod": {
    "TEXT": [
      "如果目标敌人的生命值小于等于 ", " 点，则将其生命值变为0。",
      " NL 如果目标敌人的生命值小于等于 ", " 点，则将其生命值变为0。", " 点，则将其生命值变为0。"
    ]
  },
  "FrierenMod:ChantMod": {
    "TEXT": [
      " frierenmod:咏唱 ", " 。",
      " NL  frierenmod:咏唱 ", " 。", " 。"
    ]
  },
  "FrierenMod:DexterityMod": {
    "TEXT": [
      "获得 ", " 点 敏捷 。",
      " NL 获得 ", " 点 敏捷 。", " 点 敏捷 。"
    ]
  },
  "FrierenMod:IntangibleMod": {
    "TEXT": [
      "获得 ", " 层 无实体 。 NL 消耗 。",
      " NL 获得", " 层 无实体 。 NL 消耗 。"
    ]
  },
  "FrierenMod:RemoveDebuffMod": {
    "TEXT": [
      " NL 移除你身上的所有负面效果。"
    ]
  },
  "FrierenMod:StrengthMod": {
    "TEXT": [
      " NL 将你的 力量 翻倍。 NL  消耗 。"
    ]
  },
  "FrierenMod:UpgradeMod": {
    "TEXT": [
      " NL 在本场战斗中 升级 手牌中的所有牌。"
    ]
  },
  "FrierenMod:UpgradeAllMod": {
    "TEXT": [
      " NL 在本场战斗中 升级 你的所有牌。 NL  消耗 。"
    ]
  },
  "FrierenMod:VulnerableMod": {
    "TEXT": [
      "给与所有敌人 ", " 层 易伤 。",
      " NL 给与所有敌人 ", " 层 易伤 。", " 层 易伤 。"
    ]
  },
  "FrierenMod:AnalysisMod": {
    "TEXT": [
      " frierenmod:解析 %d："," *奖励 ：","（当前进度%d/%d）。",
      " frierenmod:同调 4张 *魔力 。 NL "," !B! 点格挡。 NL ",
      " 打出3张 frierenmod:咏唱 牌 。 NL "," !M! 张本回合消耗为0的 frierenmod:传说魔法 。 NL ",
      "打出3张 frierenmod:传说魔法 。 NL "," 对所有敌人造成 !D! 点伤害。 NL "
    ]
  },
  "FrierenMod:MagicPowerMod": {
    "TEXT": [
      " frierenmod:同调 。",
      " frierenmod:加速同调 。",
      " frierenmod:终极同调 。",
      " frierenmod:终极加速同调 。"
    ]
  },
  "FrierenMod:MagicExhaustTextMod": {
    "TEXT": [
      " （消耗 %d张 *魔力 ） NL "
    ]
  },
  "FrierenMod:PatchHasEnoughEnergy": {
    "TEXT": [
      "没有足够 #r魔力 。"
    ]
  }
}